psonic/__init__.py
psonic/api.py
psonic/effects.py
psonic/notes.py
psonic/psonic.py
psonic/scales.py
psonic/synth_server.py
psonic/synthesizers.py
psonic/internals/__init__.py
psonic/internals/chords.py
psonic/internals/scales.py
psonic/samples/__init__.py
psonic/samples/ambient.py
psonic/samples/bass.py
psonic/samples/drums.py
psonic/samples/electric.py
psonic/samples/guitars.py
psonic/samples/misc.py
psonic/samples/percussions.py
psonic/samples/tabla.py
psonic/samples/vinyl.py
psonic/samples/loops/__init__.py
python_sonic-0.4.4.dist-info/LICENSE
python_sonic-0.4.4.dist-info/METADATA
python_sonic-0.4.4.dist-info/WHEEL
python_sonic-0.4.4.dist-info/top_level.txt
python_sonic-0.4.4.dist-info/RECORD
