Metadata-Version: 2.1
Name: python-sonic
Version: 0.4.4
Summary: Programming Music with Sonic Pi or Supercollider
Home-page: https://github.com/gkvoelkl/python-sonic
Author: gkvoelkl
Author-email: gkvoelkl@nelson-games.de
License: MIT
Keywords: music,sonic pi,raspberry pi,audio,music composition,scsynth,supercollider,synthesis
Classifier: Development Status :: 4 - Beta
Classifier: Intended Audience :: Developers
Classifier: Topic :: Multimedia :: Sound/Audio
Classifier: License :: OSI Approved :: MIT License
Classifier: Programming Language :: Python :: 3
Classifier: Programming Language :: Python :: 3.3
Classifier: Programming Language :: Python :: 3.4
Classifier: Programming Language :: Python :: 3.5
Classifier: Programming Language :: Python :: 3.6
Classifier: Programming Language :: Python :: 3.7
Classifier: Programming Language :: Python :: 3.8
Classifier: Programming Language :: Python :: 3.9
Classifier: Programming Language :: Python :: 3.10
Classifier: Programming Language :: Python :: 3.11
Classifier: Programming Language :: Python :: 3.12
Classifier: Programming Language :: Python :: 3.13
License-File: LICENSE
Requires-Dist: python-osc
